Workbook
Name Appoinment_Table: Table2[]
Name Appointments: Table2[]
Name Bed_Record_Table: Table4[]
Name Bed_Table: Bed!$A$6
Name Department_Table: Table5[#All]
Name Doctor_Table: Table6[#All]
Name Medical_Record_Table: Table8[#All]
Name MedicineInfo: MedicineInfo!$F$26
Name Patient_Table: Table7[]
Name Room_Info: Table10[#All]
Name Room_Records: Table12[#All]
Name Staff_Info_Table: Table9[#All]
Name Ward_Info: Table11[#All]

Sheet Appointment
A1: appoIntment_Id | B1: patient_Id | C1: doct_Id | D1: reason | E1: appointment_Date | F1: payment_amount | G1: mode_of_payment | H1: mode_of_appointment | I1: Appointment_Time | J1: Time_Slot | K1: appointment_status | L1: Attendence_Type | M1: No_Show_Flag | N1: Weekday | O1: Day_Status
A2: 5000 | B2: 1057 | C2: 1027 | D2: Back Pain | E2: 45623 | F2: 2139 | G2: Insurance | H2: Call | I2: 17:30 | J2: {=_xlfn.IFS(HOUR(I2)<12,"Morning",HOUR(I2)<17,"Afternoon",TRUE,"Evening")} -> Evening | K2: Completed | L2: =IF(K2="completed","Attended","No Show") -> Attended | M2: =IF(L2="No Show",1,0) -> 0 | N2: =TEXT(E2,"dddd") -> Wednesday | O2: =IF(OR(Table2[[#This Row],[Weekday]]="Monday",Table2[[#This Row],[Weekday]]="Tuesday",Table2[[#This Row],[Weekday]]="Wednesday",Table2[[#This Row],[Weekday]]="Thursday",Table2[[#This Row],[Weekday]]="Friday"),"Weekday","Weekend") -> Weekday
A3: 5001 | B3: 1568 | C3: 1009 | D3: Migraine | E3: 45559 | F3: 1204 | G3: Card | H3: In Person | I3: 10:30 | J3: {=_xlfn.IFS(HOUR(I3)<12,"Morning",HOUR(I3)<17,"Afternoon",TRUE,"Evening")} -> Morning | K3: Completed | L3: =IF(K3="completed","Attended","No Show") -> Attended | M3: =IF(L3="No Show",1,0) -> 0 | N3: =TEXT(E3,"dddd") -> Tuesday | O3: =IF(OR(Table2[[#This Row],[Weekday]]="Monday",Table2[[#This Row],[Weekday]]="Tuesday",Table2[[#This Row],[Weekday]]="Wednesday",Table2[[#This Row],[Weekday]]="Thursday",Table2[[#This Row],[Weekday]]="Friday"),"Weekday","Weekend") -> Weekday
A4: 5002 | B4: 449 | C4: 1024 | D4: Diabetes | E4: 45542 | F4: 2474 | G4: Digital Wallet | H4: Call | I4: 16:30 | J4: {=_xlfn.IFS(HOUR(I4)<12,"Morning",HOUR(I4)<17,"Afternoon",TRUE,"Evening")} -> Afternoon | K4: Completed | L4: =IF(K4="completed","Attended","No Show") -> Attended | M4: =IF(L4="No Show",1,0) -> 0 | N4: =TEXT(E4,"dddd") -> Saturday | O4: =IF(OR(Table2[[#This Row],[Weekday]]="Monday",Table2[[#This Row],[Weekday]]="Tuesday",Table2[[#This Row],[Weekday]]="Wednesday",Table2[[#This Row],[Weekday]]="Thursday",Table2[[#This Row],[Weekday]]="Friday"),"Weekday","Weekend") -> Weekend
A5: 5003 | B5: 279 | C5: 1008 | D5: Migraine | E5: 45807 | F5: 1148 | G5: Insurance | H5: Call | I5: 13:15 | J5: {=_xlfn.IFS(HOUR(I5)<12,"Morning",HOUR(I5)<17,"Afternoon",TRUE,"Evening")} -> Afternoon | K5: Completed | L5: =IF(K5="completed","Attended","No Show") -> Attended | M5: =IF(L5="No Show",1,0) -> 0 | N5: =TEXT(E5,"dddd") -> Friday | O5: =IF(OR(Table2[[#This Row],[Weekday]]="Monday",Table2[[#This Row],[Weekday]]="Tuesday",Table2[[#This Row],[Weekday]]="Wednesday",Table2[[#This Row],[Weekday]]="Thursday",Table2[[#This Row],[Weekday]]="Friday"),"Weekday","Weekend") -> Weekday
A6: 5004 | B6: 1089 | C6: 1001 | D6: Hypertension | E6: 45560 | F6: 2031 | G6: Insurance | H6: Online | I6: 11:15 | J6: {=_xlfn.IFS(HOUR(I6)<12,"Morning",HOUR(I6)<17,"Afternoon",TRUE,"Evening")} -> Morning | K6: Cancelled | L6: =IF(K6="completed","Attended","No Show") -> No Show | M6: =IF(L6="No Show",1,0) -> 1 | N6: =TEXT(E6,"dddd") -> Wednesday | O6: =IF(OR(Table2[[#This Row],[Weekday]]="Monday",Table2[[#This Row],[Weekday]]="Tuesday",Table2[[#This Row],[Weekday]]="Wednesday",Table2[[#This Row],[Weekday]]="Thursday",Table2[[#This Row],[Weekday]]="Friday"),"Weekday","Weekend") -> Weekday
A7: 5005 | B7: 450 | C7: 1009 | D7: Migraine | E7: 45489 | F7: 2246 | G7: Card | H7: Call | I7: 16:45 | J7: {=_xlfn.IFS(HOUR(I7)<12,"Morning",HOUR(I7)<17,"Afternoon",TRUE,"Evening")} -> Afternoon | K7: Completed | L7: =IF(K7="completed","Attended","No Show") -> Attended | M7: =IF(L7="No Show",1,0) -> 0 | N7: =TEXT(E7,"dddd") -> Tuesday | O7: =IF(OR(Table2[[#This Row],[Weekday]]="Monday",Table2[[#This Row],[Weekday]]="Tuesday",Table2[[#This Row],[Weekday]]="Wednesday",Table2[[#This Row],[Weekday]]="Thursday",Table2[[#This Row],[Weekday]]="Friday"),"Weekday","Weekend") -> Weekday
A8: 5006 | B8: 540 | C8: 1027 | D8: Headache | E8: 45657 | F8: 2487 | G8: Card | H8: Online | I8: 18:30 | J8: {=_xlfn.IFS(HOUR(I8)<12,"Morning",HOUR(I8)<17,"Afternoon",TRUE,"Evening")} -> Evening | K8: Completed | L8: =IF(K8="completed","Attended","No Show") -> Attended | M8: =IF(L8="No Show",1,0) -> 0 | N8: =TEXT(E8,"dddd") -> Tuesday | O8: =IF(OR(Table2[[#This Row],[Weekday]]="Monday",Table2[[#This Row],[Weekday]]="Tuesday",Table2[[#This Row],[Weekday]]="Wednesday",Table2[[#This Row],[Weekday]]="Thursday",Table2[[#This Row],[Weekday]]="Friday"),"Weekday","Weekend") -> Weekday
A9: 5007 | B9: 1309 | C9: 1027 | D9: Chest Pain | E9: 45819 | F9: 867 | G9: Card | H9: Online | I9: 10:45 | J9: {=_xlfn.IFS(HOUR(I9)<12,"Morning",HOUR(I9)<17,"Afternoon",TRUE,"Evening")} -> Morning | K9: Scheduled | L9: =IF(K9="completed","Attended","No Show") -> No Show | M9: =IF(L9="No Show",1,0) -> 1 | N9: =TEXT(E9,"dddd") -> Wednesday | O9: =IF(OR(Table2[[#This Row],[Weekday]]="Monday",Table2[[#This Row],[Weekday]]="Tuesday",Table2[[#This Row],[Weekday]]="Wednesday",Table2[[#This Row],[Weekday]]="Thursday",Table2[[#This Row],[Weekday]]="Friday"),"Weekday","Weekend") -> Weekday
A10: 5008 | B10: 734 | C10: 1027 | D10: General Checkup | E10: 45590 | F10: 1682 | G10: Cash | H10: Online | I10: 10:15 | J10: {=_xlfn.IFS(HOUR(I10)<12,"Morning",HOUR(I10)<17,"Afternoon",TRUE,"Evening")} -> Morning | K10: Completed | L10: =IF(K10="completed","Attended","No Show") -> Attended | M10: =IF(L10="No Show",1,0) -> 0 | N10: =TEXT(E10,"dddd") -> Friday | O10: =IF(OR(Table2[[#This Row],[Weekday]]="Monday",Table2[[#This Row],[Weekday]]="Tuesday",Table2[[#This Row],[Weekday]]="Wednesday",Table2[[#This Row],[Weekday]]="Thursday",Table2[[#This Row],[Weekday]]="Friday"),"Weekday","Weekend") -> Weekday
A11: 5009 | B11: 927 | C11: 1020 | D11: Asthma | E11: 45765 | F11: 2010 | G11: Card | H11: Online | I11: 9:45 | J11: {=_xlfn.IFS(HOUR(I11)<12,"Morning",HOUR(I11)<17,"Afternoon",TRUE,"Evening")} -> Morning | K11: Completed | L11: =IF(K11="completed","Attended","No Show") -> Attended | M11: =IF(L11="No Show",1,0) -> 0 | N11: =TEXT(E11,"dddd") -> Friday | O11: =IF(OR(Table2[[#This Row],[Weekday]]="Monday",Table2[[#This Row],[Weekday]]="Tuesday",Table2[[#This Row],[Weekday]]="Wednesday",Table2[[#This Row],[Weekday]]="Thursday",Table2[[#This Row],[Weekday]]="Friday"),"Weekday","Weekend") -> Weekday
A12: 5010 | B12: 228 | C12: 1027 | D12: General Checkup | E12: 45715 | F12: 2412 | G12: Cash | H12: Online | I12: 13:45 | J12: {=_xlfn.IFS(HOUR(I12)<12,"Morning",HOUR(I12)<17,"Afternoon",TRUE,"Evening")} -> Afternoon | K12: Cancelled | L12: =IF(K12="completed","Attended","No Show") -> No Show | M12: =IF(L12="No Show",1,0) -> 1 | N12: =TEXT(E12,"dddd") -> Thursday | O12: =IF(OR(Table2[[#This Row],[Weekday]]="Monday",Table2[[#This Row],[Weekday]]="Tuesday",Table2[[#This Row],[Weekday]]="Wednesday",Table2[[#This Row],[Weekday]]="Thursday",Table2[[#This Row],[Weekday]]="Friday"),"Weekday","Weekend") -> Weekday
A13: 5011 | B13: 464 | C13: 1027 | D13: Fever | E13: 45654 | F13: 1110 | G13: Insurance | H13: In Person | I13: 17:30 | J13: {=_xlfn.IFS(HOUR(I13)<12,"Morning",HOUR(I13)<17,"Afternoon",TRUE,"Evening")} -> Evening | K13: Completed | L13: =IF(K13="completed","Attended","No Show") -> Attended | M13: =IF(L13="No Show",1,0) -> 0 | N13: =TEXT(E13,"dddd") -> Saturday | O13: =IF(OR(Table2[[#This Row],[Weekday]]="Monday",Table2[[#This Row],[Weekday]]="Tuesday",Table2[[#This Row],[Weekday]]="Wednesday",Table2[[#This Row],[Weekday]]="Thursday",Table2[[#This Row],[Weekday]]="Friday"),"Weekday","Weekend") -> Weekend
... A1001: 5999 | B1001: 1412 | C1001: 1027 | D1001: Headache | E1001: 45826 | F1001: 2287 | G1001: Insurance | H1001: Online | I1001: 17:30 | J1001: {=_xlfn.IFS(HOUR(I1001)<12,"Morning",HOUR(I1001)<17,"Afternoon",TRUE,"Evening")} -> Evening | K1001: Scheduled | L1001: =IF(K1001="completed","Attended","No Show") -> No Show | M1001: =IF(L1001="No Show",1,0) -> 1 | N1001: =TEXT(E1001,"dddd") -> Wednesday | O1001: =IF(OR(Table2[[#This Row],[Weekday]]="Monday",Table2[[#This Row],[Weekday]]="Tuesday",Table2[[#This Row],[Weekday]]="Wednesday",Table2[[#This Row],[Weekday]]="Thursday",Table2[[#This Row],[Weekday]]="Friday"),"Weekday","Weekend") -> Weekday

Sheet Department
A1: dept_Id | B1: dept_Name
A2: 101 | B2: Cardiology
A3: 102 | B3: Neurology
A4: 103 | B4: Gastroenterology
A5: 104 | B5: Nephrology
A6: 105 | B6: Pulmonology
A7: 106 | B7: Endocrinology
A8: 107 | B8: General Medicine
A9: 108 | B9: Pediatrics
A10: 109 | B10: Orthopedics
A11: 110 | B11: Gynecology
A12: 111 | B12: Dentistry
A13: 112 | B13: Dermatology
... A32: 131 | B32: Geriatrics

Sheet Doctor
A1: doct_Id | B1: dept_Id | C1: Doctor_Name | D1: Gender | E1: contact_No | F1: Leaves | G1: Salary
A2: 1001 | B2: 101 | C2: Aditya Kulkarni | D2: Male | E2: +91 9724234590 | F2: 22 | G2: 97704
A3: 1002 | B3: 101 | C3: Ananya Deshpande | D3: Female | E3: +91 9690647248 | F3: 20 | G3: 98756
A4: 1003 | B4: 101 | C4: Nikhil Bhosale | D4: Male | E4: +91 9646357075 | F4: 29 | G4: 98656
A5: 1004 | B5: 101 | C5: Siddharth Joshi | D5: Male | E5: +91 9323953542 | F5: 27 | G5: 76709
A6: 1006 | B6: 101 | C6: Rohan Deshmukh | D6: Male | E6: +91 9218724015 | F6: 8 | G6: 143987
A7: 1008 | B7: 102 | C7: Rahul Wankhede | D7: Male | E7: +91 9816064456 | F7: 12 | G7: 114017
A8: 1009 | B8: 102 | C8: Shruti Borkar | D8: Female | E8: +91 9307523998 | F8: 25 | G8: 116783
A9: 1010 | B9: 102 | C9: Ananya Deshpande | D9: Female | E9: +91 9923079267 | F9: 14 | G9: 76148
A10: 1011 | B10: 102 | C10: Priya More | D10: Female | E10: +91 9272229987 | F10: 9 | G10: 56761
A11: 1012 | B11: 102 | C11: Siddharth Joshi | D11: Male | E11: +91 9236463590 | F11: 11 | G11: 108349
A12: 1013 | B12: 103 | C12: Kavita Wagh | D12: Female | E12: +91 9659097422 | F12: 25 | G12: 123242
A13: 1014 | B13: 103 | C13: Omkar Pawar | D13: Male | E13: +91 9342176125 | F13: 29 | G13: 97091
... A219: 1399 | B219: 131 | C219: Aditya Kulkarni | D219: Male | E219: +91 9224771537 | F219: 24 | G219: 100628

Sheet Patients
A1: patient_Id | B1: Patient_Name | C1: Gender | D1: Date_Of_Birth | E1: contact_No | F1: City
A2: 100 | B2: Siddharth Joshi | C2: Male | D2: 18823 | E2: +91 9305902102 | F2: Pusad
A3: 101 | B3: Pooja Shinde | C3: Female | D3: 35026 | E3: +91 9964107254 | F3: Nagpur
A4: 102 | B4: Rohan Deshmukh | C4: Male | D4: 44196 | E4: +91 9458638670 | F4: Amravati
A5: 103 | B5: Vikram Shinde | C5: Male | D5: 13302 | E5: +91 9374467902 | F5: Akola
A6: 104 | B6: Nikhil Bhosale | C6: Male | D6: 11183 | E6: +91 9413401111 | F6: Akola
A7: 105 | B7: Sneha Patil | C7: Female | D7: 20996 | E7: +91 9527257879 | F7: Yavatmal
A8: 106 | B8: Vikram Shinde | C8: Male | D8: 22026 | E8: +91 9626828608 | F8: Nagpur
A9: 107 | B9: Priya More | C9: Female | D9: 30098 | E9: +91 9103684849 | F9: Wardha
A10: 108 | B10: Aarav Patil | C10: Male | D10: 41433 | E10: +91 9120574279 | F10: Pusad
A11: 109 | B11: Priya More | C11: Female | D11: 23905 | E11: +91 9864233661 | F11: Nanded
A12: 110 | B12: Shruti Borkar | C12: Female | D12: 30232 | E12: +91 9327077001 | F12: Nagpur
A13: 111 | B13: Ishita Kulkarni | C13: Female | D13: 28466 | E13: +91 9860412846 | F13: Akola
... A1501: 1599 | B1501: Pooja Shinde | C1501: Female | D1501: 31276 | E1501: +91 9552328228 | F1501: Chandrapur

Sheet MedicalRecord
A1: record_Id | B1: doct_Id | C1: patient_Id | D1: visit_Date | E1: diagnosis | F1: treatment | G1: Medicines | H1: next_Visit | I1: Follow_UP_Status | J1: Visit_Day | K1: Visit_Month | L1: Seasons
A2: 1 | B2: 1027 | C2: 1057 | D2: 45823 | E2: Lumbar Strain | F2: Physical Therapy, NSAIDs | G2: =_xlfn.XLOOKUP(TRIM(E3),MedicineInfo!A:A,MedicineInfo!B:B,"Not Found") -> Sumatriptan | H2: {=_xlfn.IFS( OR(E2="Type 2 Diabetes",E2="Essential Hypertension",E2="Angina Pectoris",E2="Bronchial Asthma",E2="Cardiac Arrhythmia"), D2+30, OR(E2="Gastritis",E2="Osteoarthritis",E2="Bronchitis",E2="Iron Deficiency Anemia"), D2+14, OR(E2="Lumbar Strain",E2="Migraine Headache"), D2+7, OR(E2="Viral Fever",E2="General Checkup","Routine Health Check"), "", TRUE,"" )} -> 45830 | I2: =IF(H2="","No Follow-up Required","Follow-up Scheduled") -> Follow-up Scheduled | J2: =TEXT(Table8[[#This Row],[visit_Date]],"DDDD") -> Sunday | K2: =TEXT(Table8[[#This Row],[visit_Date]],"mmmm") -> June | L2: =IF(OR(MONTH(D2)=12,MONTH(D2)<=2),"Winter", IF(MONTH(D2)<=5,"Summer","Monsoon")) -> Monsoon
A3: 2 | B3: 1009 | C3: 1568 | D3: 45823 | E3: Migraine Headache | F3: Triptans, Rest | G3: =_xlfn.XLOOKUP(TRIM(E4),MedicineInfo!A:A,MedicineInfo!B:B,"Not Found") -> Metformin | H3: {=_xlfn.IFS( OR(E3="Type 2 Diabetes",E3="Essential Hypertension",E3="Angina Pectoris",E3="Bronchial Asthma",E3="Cardiac Arrhythmia"), D3+30, OR(E3="Gastritis",E3="Osteoarthritis",E3="Bronchitis",E3="Iron Deficiency Anemia"), D3+14, OR(E3="Lumbar Strain",E3="Migraine Headache"), D3+7, OR(E3="Viral Fever",E3="General Checkup","Routine Health Check"), "", TRUE,"" )} -> 45830 | I3: =IF(H3="","No Follow-up Required","Follow-up Scheduled") -> Follow-up Scheduled | J3: =TEXT(Table8[[#This Row],[visit_Date]],"DDDD") -> Sunday | K3: =TEXT(Table8[[#This Row],[visit_Date]],"mmmm") -> June | L3: =IF(OR(MONTH(D3)=12,MONTH(D3)<=2),"Winter", IF(MONTH(D3)<=5,"Summer","Monsoon")) -> Monsoon
A4: 3 | B4: 1024 | C4: 449 | D4: 45758 | E4: Type 2 Diabetes | F4: Metformin, Diet Control | G4: =_xlfn.XLOOKUP(TRIM(E5),MedicineInfo!A:A,MedicineInfo!B:B,"Not Found") -> Sumatriptan | H4: {=_xlfn.IFS( OR(E4="Type 2 Diabetes",E4="Essential Hypertension",E4="Angina Pectoris",E4="Bronchial Asthma",E4="Cardiac Arrhythmia"), D4+30, OR(E4="Gastritis",E4="Osteoarthritis",E4="Bronchitis",E4="Iron Deficiency Anemia"), D4+14, OR(E4="Lumbar Strain",E4="Migraine Headache"), D4+7, OR(E4="Viral Fever",E4="General Checkup","Routine Health Check"), "", TRUE,"" )} -> 45788 | I4: =IF(H4="","No Follow-up Required","Follow-up Scheduled") -> Follow-up Scheduled | J4: =TEXT(Table8[[#This Row],[visit_Date]],"DDDD") -> Friday | K4: =TEXT(Table8[[#This Row],[visit_Date]],"mmmm") -> April | L4: =IF(OR(MONTH(D4)=12,MONTH(D4)<=2),"Winter", IF(MONTH(D4)<=5,"Summer","Monsoon")) -> Summer
A5: 4 | B5: 1008 | C5: 279 | D5: 45767 | E5: Migraine Headache | F5: Triptans, Rest | G5: =_xlfn.XLOOKUP(TRIM(E6),MedicineInfo!A:A,MedicineInfo!B:B,"Not Found") -> Amlodipine | H5: {=_xlfn.IFS( OR(E5="Type 2 Diabetes",E5="Essential Hypertension",E5="Angina Pectoris",E5="Bronchial Asthma",E5="Cardiac Arrhythmia"), D5+30, OR(E5="Gastritis",E5="Osteoarthritis",E5="Bronchitis",E5="Iron Deficiency Anemia"), D5+14, OR(E5="Lumbar Strain",E5="Migraine Headache"), D5+7, OR(E5="Viral Fever",E5="General Checkup","Routine Health Check"), "", TRUE,"" )} -> 45774 | I5: =IF(H5="","No Follow-up Required","Follow-up Scheduled") -> Follow-up Scheduled | J5: =TEXT(Table8[[#This Row],[visit_Date]],"DDDD") -> Sunday | K5: =TEXT(Table8[[#This Row],[visit_Date]],"mmmm") -> April | L5: =IF(OR(MONTH(D5)=12,MONTH(D5)<=2),"Winter", IF(MONTH(D5)<=5,"Summer","Monsoon")) -> Summer
A6: 5 | B6: 1001 | C6: 1089 | D6: 45814 | E6: Essential Hypertension | F6: ACE Inhibitors, Lifestyle Changes | G6: =_xlfn.XLOOKUP(TRIM(E7),MedicineInfo!A:A,MedicineInfo!B:B,"Not Found") -> Sumatriptan | H6: {=_xlfn.IFS( OR(E6="Type 2 Diabetes",E6="Essential Hypertension",E6="Angina Pectoris",E6="Bronchial Asthma",E6="Cardiac Arrhythmia"), D6+30, OR(E6="Gastritis",E6="Osteoarthritis",E6="Bronchitis",E6="Iron Deficiency Anemia"), D6+14, OR(E6="Lumbar Strain",E6="Migraine Headache"), D6+7, OR(E6="Viral Fever",E6="General Checkup","Routine Health Check"), "", TRUE,"" )} -> 45844 | I6: =IF(H6="","No Follow-up Required","Follow-up Scheduled") -> Follow-up Scheduled | J6: =TEXT(Table8[[#This Row],[visit_Date]],"DDDD") -> Friday | K6: =TEXT(Table8[[#This Row],[visit_Date]],"mmmm") -> June | L6: =IF(OR(MONTH(D6)=12,MONTH(D6)<=2),"Winter", IF(MONTH(D6)<=5,"Summer","Monsoon")) -> Monsoon
A7: 6 | B7: 1009 | C7: 450 | D7: 45759 | E7: Migraine Headache | F7: Triptans, Rest | G7: =_xlfn.XLOOKUP(TRIM(E8),MedicineInfo!A:A,MedicineInfo!B:B,"Not Found") -> Multivitamin | H7: {=_xlfn.IFS( OR(E7="Type 2 Diabetes",E7="Essential Hypertension",E7="Angina Pectoris",E7="Bronchial Asthma",E7="Cardiac Arrhythmia"), D7+30, OR(E7="Gastritis",E7="Osteoarthritis",E7="Bronchitis",E7="Iron Deficiency Anemia"), D7+14, OR(E7="Lumbar Strain",E7="Migraine Headache"), D7+7, OR(E7="Viral Fever",E7="General Checkup","Routine Health Check"), "", TRUE,"" )} -> 45766 | I7: =IF(H7="","No Follow-up Required","Follow-up Scheduled") -> Follow-up Scheduled | J7: =TEXT(Table8[[#This Row],[visit_Date]],"DDDD") -> Saturday | K7: =TEXT(Table8[[#This Row],[visit_Date]],"mmmm") -> April | L7: =IF(OR(MONTH(D7)=12,MONTH(D7)<=2),"Winter", IF(MONTH(D7)<=5,"Summer","Monsoon")) -> Summer
A8: 7 | B8: 1027 | C8: 540 | D8: 45719 | E8: General Checkup | F8: Advice | G8: =_xlfn.XLOOKUP(TRIM(E9),MedicineInfo!A:A,MedicineInfo!B:B,"Not Found") -> Nitroglycerin | H8: {=_xlfn.IFS( OR(E8="Type 2 Diabetes",E8="Essential Hypertension",E8="Angina Pectoris",E8="Bronchial Asthma",E8="Cardiac Arrhythmia"), D8+30, OR(E8="Gastritis",E8="Osteoarthritis",E8="Bronchitis",E8="Iron Deficiency Anemia"), D8+14, OR(E8="Lumbar Strain",E8="Migraine Headache"), D8+7, OR(E8="Viral Fever",E8="General Checkup","Routine Health Check"), "", TRUE,"" )} | I8: =IF(H8="","No Follow-up Required","Follow-up Scheduled") -> No Follow-up Required | J8: =TEXT(Table8[[#This Row],[visit_Date]],"DDDD") -> Monday | K8: =TEXT(Table8[[#This Row],[visit_Date]],"mmmm") -> March | L8: =IF(OR(MONTH(D8)=12,MONTH(D8)<=2),"Winter", IF(MONTH(D8)<=5,"Summer","Monsoon")) -> Summer
A9: 8 | B9: 1027 | C9: 1309 | D9: 45758 | E9: Angina Pectoris | F9: Nitroglycerin, Beta Blockers | G9: =_xlfn.XLOOKUP(TRIM(E10),MedicineInfo!A:A,MedicineInfo!B:B,"Not Found") -> Multivitamin | H9: {=_xlfn.IFS( OR(E9="Type 2 Diabetes",E9="Essential Hypertension",E9="Angina Pectoris",E9="Bronchial Asthma",E9="Cardiac Arrhythmia"), D9+30, OR(E9="Gastritis",E9="Osteoarthritis",E9="Bronchitis",E9="Iron Deficiency Anemia"), D9+14, OR(E9="Lumbar Strain",E9="Migraine Headache"), D9+7, OR(E9="Viral Fever",E9="General Checkup","Routine Health Check"), "", TRUE,"" )} -> 45788 | I9: =IF(H9="","No Follow-up Required","Follow-up Scheduled") -> Follow-up Scheduled | J9: =TEXT(Table8[[#This Row],[visit_Date]],"DDDD") -> Friday | K9: =TEXT(Table8[[#This Row],[visit_Date]],"mmmm") -> April | L9: =IF(OR(MONTH(D9)=12,MONTH(D9)<=2),"Winter", IF(MONTH(D9)<=5,"Summer","Monsoon")) -> Summer
A10: 9 | B10: 1027 | C10: 734 | D10: 45853 | E10: General Checkup | F10: Advice | G10: =_xlfn.XLOOKUP(TRIM(E11),MedicineInfo!A:A,MedicineInfo!B:B,"Not Found") -> Salbutamol Inhaler | H10: {=_xlfn.IFS( OR(E10="Type 2 Diabetes",E10="Essential Hypertension",E10="Angina Pectoris",E10="Bronchial Asthma",E10="Cardiac Arrhythmia"), D10+30, OR(E10="Gastritis",E10="Osteoarthritis",E10="Bronchitis",E10="Iron Deficiency Anemia"), D10+14, OR(E10="Lumbar Strain",E10="Migraine Headache"), D10+7, OR(E10="Viral Fever",E10="General Checkup","Routine Health Check"), "", TRUE,"" )} | I10: =IF(H10="","No Follow-up Required","Follow-up Scheduled") -> No Follow-up Required | J10: =TEXT(Table8[[#This Row],[visit_Date]],"DDDD") -> Tuesday | K10: =TEXT(Table8[[#This Row],[visit_Date]],"mmmm") -> July | L10: =IF(OR(MONTH(D10)=12,MONTH(D10)<=2),"Winter", IF(MONTH(D10)<=5,"Summer","Monsoon")) -> Monsoon
A11: 10 | B11: 1020 | C11: 927 | D11: 45712 | E11: Bronchial Asthma | F11: Inhaled Corticosteroids | G11: =_xlfn.XLOOKUP(TRIM(E12),MedicineInfo!A:A,MedicineInfo!B:B,"Not Found") -> Multivitamin | H11: {=_xlfn.IFS( OR(E11="Type 2 Diabetes",E11="Essential Hypertension",E11="Angina Pectoris",E11="Bronchial Asthma",E11="Cardiac Arrhythmia"), D11+30, OR(E11="Gastritis",E11="Osteoarthritis",E11="Bronchitis",E11="Iron Deficiency Anemia"), D11+14, OR(E11="Lumbar Strain",E11="Migraine Headache"), D11+7, OR(E11="Viral Fever",E11="General Checkup","Routine Health Check"), "", TRUE,"" )} -> 45742 | I11: =IF(H11="","No Follow-up Required","Follow-up Scheduled") -> Follow-up Scheduled | J11: =TEXT(Table8[[#This Row],[visit_Date]],"DDDD") -> Monday | K11: =TEXT(Table8[[#This Row],[visit_Date]],"mmmm") -> February | L11: =IF(OR(MONTH(D11)=12,MONTH(D11)<=2),"Winter", IF(MONTH(D11)<=5,"Summer","Monsoon")) -> Winter
A12: 11 | B12: 1027 | C12: 228 | D12: 45731 | E12: General Checkup | F12: Advice | G12: =_xlfn.XLOOKUP(TRIM(E13),MedicineInfo!A:A,MedicineInfo!B:B,"Not Found") -> Paracetamol | H12: {=_xlfn.IFS( OR(E12="Type 2 Diabetes",E12="Essential Hypertension",E12="Angina Pectoris",E12="Bronchial Asthma",E12="Cardiac Arrhythmia"), D12+30, OR(E12="Gastritis",E12="Osteoarthritis",E12="Bronchitis",E12="Iron Deficiency Anemia"), D12+14, OR(E12="Lumbar Strain",E12="Migraine Headache"), D12+7, OR(E12="Viral Fever",E12="General Checkup","Routine Health Check"), "", TRUE,"" )} | I12: =IF(H12="","No Follow-up Required","Follow-up Scheduled") -> No Follow-up Required | J12: =TEXT(Table8[[#This Row],[visit_Date]],"DDDD") -> Saturday | K12: =TEXT(Table8[[#This Row],[visit_Date]],"mmmm") -> March | L12: =IF(OR(MONTH(D12)=12,MONTH(D12)<=2),"Winter", IF(MONTH(D12)<=5,"Summer","Monsoon")) -> Summer
A13: 12 | B13: 1027 | C13: 464 | D13: 45830 | E13: Viral Fever | F13: Paracetamol, Rest | G13: =_xlfn.XLOOKUP(TRIM(E14),MedicineInfo!A:A,MedicineInfo!B:B,"Not Found") -> Multivitamin | H13: {=_xlfn.IFS( OR(E13="Type 2 Diabetes",E13="Essential Hypertension",E13="Angina Pectoris",E13="Bronchial Asthma",E13="Cardiac Arrhythmia"), D13+30, OR(E13="Gastritis",E13="Osteoarthritis",E13="Bronchitis",E13="Iron Deficiency Anemia"), D13+14, OR(E13="Lumbar Strain",E13="Migraine Headache"), D13+7, OR(E13="Viral Fever",E13="General Checkup","Routine Health Check"), "", TRUE,"" )} | I13: =IF(H13="","No Follow-up Required","Follow-up Scheduled") -> No Follow-up Required | J13: =TEXT(Table8[[#This Row],[visit_Date]],"DDDD") -> Sunday | K13: =TEXT(Table8[[#This Row],[visit_Date]],"mmmm") -> June | L13: =IF(OR(MONTH(D13)=12,MONTH(D13)<=2),"Winter", IF(MONTH(D13)<=5,"Summer","Monsoon")) -> Monsoon
... A3001: 3000 | B3001: 1201 | C3001: 571 | D3001: 45696 | E3001: General Checkup | F3001: Advice | G3001: =_xlfn.XLOOKUP(TRIM(E3002),MedicineInfo!A:A,MedicineInfo!B:B,"Not Found") -> Not Found | H3001: {=_xlfn.IFS( OR(E3001="Type 2 Diabetes",E3001="Essential Hypertension",E3001="Angina Pectoris",E3001="Bronchial Asthma",E3001="Cardiac Arrhythmia"), D3001+30, OR(E3001="Gastritis",E3001="Osteoarthritis",E3001="Bronchitis",E3001="Iron Deficiency Anemia"), D3001+14, OR(E3001="Lumbar Strain",E3001="Migraine Headache"), D3001+7, OR(E3001="Viral Fever",E3001="General Checkup","Routine Health Check"), "", TRUE,"" )} | I3001: =IF(H3001="","No Follow-up Required","Follow-up Scheduled") -> No Follow-up Required | J3001: =TEXT(Table8[[#This Row],[visit_Date]],"DDDD") -> Saturday | K3001: =TEXT(Table8[[#This Row],[visit_Date]],"mmmm") -> February | L3001: =IF(OR(MONTH(D3001)=12,MONTH(D3001)<=2),"Winter", IF(MONTH(D3001)<=5,"Summer","Monsoon")) -> Winter

Sheet MedicineInfo
A1: Diagnosis | B1: Medicine | C1: Price (₹) | D1: MFG_Date | E1: Expiry_Date | F1: Medicine_Stock | G1: Stock_Status
A2: Lumbar Strain | B2: Diclofenac | C2: 120 | D2: 45658 | E2: 46388 | F2: 107 | G2: =IF(F2=0,"Out of Stock", IF(F2<=40,"Low Stock", IF(F2<=120,"Available","Overstock"))) -> Available
A3: Migraine Headache | B3: Sumatriptan | C3: 250 | D3: 45703 | E3: 46433 | F3: 109 | G3: =IF(F3=0,"Out of Stock", IF(F3<=40,"Low Stock", IF(F3<=120,"Available","Overstock"))) -> Available
A4: Type 2 Diabetes | B4: Metformin | C4: 180 | D4: 45726 | E4: 46456 | F4: 197 | G4: =IF(F4=0,"Out of Stock", IF(F4<=40,"Low Stock", IF(F4<=120,"Available","Overstock"))) -> Overstock
A5: Essential Hypertension | B5: Amlodipine | C5: 150 | D5: 45677 | E5: 46407 | F5: 93 | G5: =IF(F5=0,"Out of Stock", IF(F5<=40,"Low Stock", IF(F5<=120,"Available","Overstock"))) -> Available
A6: Bronchial Asthma | B6: Salbutamol Inhaler | C6: 320 | D6: 45752 | E6: 46482 | F6: 173 | G6: =IF(F6=0,"Out of Stock", IF(F6<=40,"Low Stock", IF(F6<=120,"Available","Overstock"))) -> Overstock
A7: Viral Fever | B7: Paracetamol | C7: 60 | D7: 45789 | E7: 46519 | F7: 107 | G7: =IF(F7=0,"Out of Stock", IF(F7<=40,"Low Stock", IF(F7<=120,"Available","Overstock"))) -> Available
A8: Angina Pectoris | B8: Nitroglycerin | C8: 410 | D8: 45706 | E8: 46436 | F8: 168 | G8: =IF(F8=0,"Out of Stock", IF(F8<=40,"Low Stock", IF(F8<=120,"Available","Overstock"))) -> Overstock
A9: General Checkup | B9: Multivitamin | C9: 90 | D9: 45741 | E9: 46471 | F9: 178 | G9: =IF(F9=0,"Out of Stock", IF(F9<=40,"Low Stock", IF(F9<=120,"Available","Overstock"))) -> Overstock
A10: Gastritis | B10: Pantoprazole | C10: 140 | D10: 45734 | E10: 46464 | F10: 45 | G10: =IF(F10=0,"Out of Stock", IF(F10<=40,"Low Stock", IF(F10<=120,"Available","Overstock"))) -> Available
A11: Osteoarthritis | B11: Aceclofenac | C11: 210 | D11: 45695 | E11: 46425 | F11: 40 | G11: =IF(F11=0,"Out of Stock", IF(F11<=40,"Low Stock", IF(F11<=120,"Available","Overstock"))) -> Low Stock
A12: Iron Deficiency Anemia | B12: Ferrous Sulfate | C12: 110 | D12: 45679 | E12: 46409 | F12: 132 | G12: =IF(F12=0,"Out of Stock", IF(F12<=40,"Low Stock", IF(F12<=120,"Available","Overstock"))) -> Overstock
A13: Hypothyroidism | B13: Levothyroxine | C13: 190 | D13: 45819 | E13: 46549 | F13: 76 | G13: =IF(F13=0,"Out of Stock", IF(F13<=40,"Low Stock", IF(F13<=120,"Available","Overstock"))) -> Available
... A26: Developmental Language Disorder | B26: Neuro Vitamins | C26: 210 | D26: 45759 | E26: 46489 | F26: 84 | G26: =IF(F26=0,"Out of Stock", IF(F26<=40,"Low Stock", IF(F26<=120,"Available","Overstock"))) -> Available

Sheet Staff
A1: Staff_Id | B1: dept_Id | C1: Staff_Name | D1: Gender | E1: contact_No | F1: Joining_date | G1: Working_Days | H1: Leaves_Taken | I1: Salary
A2: 3001 | B2: 101 | C2: Siddharth Joshi | D2: Male | E2: +91 9305902102 | F2: 43795.855 | G2: 342 | H2: 23 | I2: 28395
A3: 3002 | B3: 101 | C3: Ananya Deshpande | D3: Female | E3: +91 9964107254 | F3: 45159.93 | G3: 351 | H3: 14 | I3: 18361
A4: 3003 | B4: 101 | C4: Sneha Patil | D4: Female | E4: +91 9458638670 | F4: 43767.585 | G4: 350 | H4: 15 | I4: 29279
A5: 3004 | B5: 101 | C5: Kavita Wagh | D5: Female | E5: +91 9374467902 | F5: 45573.956 | G5: 352 | H5: 13 | I5: 15132
A6: 3005 | B6: 101 | C6: Shruti Borkar | D6: Female | E6: +91 9413401111 | F6: 43165.906 | G6: 360 | H6: 5 | I6: 34996
A7: 3006 | B7: 101 | C7: Vikram Shinde | D7: Male | E7: +91 9527257879 | F7: 43010.149 | G7: 353 | H7: 12 | I7: 35548
A8: 3007 | B8: 101 | C8: Neha Jadhav | D8: Female | E8: +91 9626828608 | F8: 43700.944 | G8: 356 | H8: 9 | I8: 30318
A9: 3008 | B9: 101 | C9: Aditya Kulkarni | D9: Male | E9: +91 9103684849 | F9: 43771.054 | G9: 346 | H9: 19 | I9: 28914
A10: 3009 | B10: 101 | C10: Siddharth Joshi | D10: Male | E10: +91 9120574279 | F10: 44590.026 | G10: 357 | H10: 8 | I10: 23249
A11: 3010 | B11: 101 | C11: Rohan Deshmukh | D11: Male | E11: +91 9864233661 | F11: 43987.294 | G11: 345 | H11: 20 | I11: 27152
A12: 3011 | B12: 101 | C12: Kavita Wagh | D12: Female | E12: +91 9327077001 | F12: 43261.083 | G12: 355 | H12: 10 | I12: 33743
A13: 3012 | B13: 101 | C13: Kavita Wagh | D13: Female | E13: +91 9860412846 | F13: 43815.111 | G13: 345 | H13: 20 | I13: 28488
... A501: 3500 | B501: 131 | C501: Ananya Deshpande | D501: Female | E501: +91 9639006521 | F501: 42883.04 | G501: 345 | H501: 20 | I501: 35729

Sheet Bed
A1: bed_No | B1: ward_No
A2: 1 | B2: 501
A3: 2 | B3: 501
A4: 3 | B4: 501
A5: 4 | B5: 501
A6: 5 | B6: 501
A7: 6 | B7: 501
A8: 7 | B8: 501
A9: 8 | B9: 501
A10: 9 | B10: 501
A11: 10 | B11: 501
A12: 11 | B12: 501
A13: 12 | B13: 501
... A501: 500 | B501: 562

Sheet BedRecords
A1: admission_Id | B1: bed_No | C1: patient_Id | D1: Staff_Id | E1: admission_Date | F1: discharge_Date | G1: amount | H1: mode_of_payment
A2: 100011 | B2: 42 | C2: 1092 | D2: 3373 | E2: 45737 | F2: 45740 | G2: 32844 | H2: Insurance
A3: 100012 | B3: 273 | C3: 859 | D3: 3406 | E3: 45754 | F3: 45756 | G3: 18339 | H3: Card
A4: 100013 | B4: 252 | C4: 895 | D4: 3180 | E4: 45635 | F4: 45637 | G4: 15451 | H4: Card
A5: 100014 | B5: 363 | C5: 1288 | D5: 3064 | E5: 45793 | F5: 45797 | G5: 22463 | H5: Cash
A6: 100015 | B6: 250 | C6: 189 | D6: 3472 | E6: 45773 | F6: 45775 | G6: 18214 | H6: Card
A7: 100016 | B7: 434 | C7: 1321 | D7: 3305 | E7: 45723 | F7: 45755 | G7: 214065 | H7: Digital Wallet
A8: 100017 | B8: 94 | C8: 1429 | D8: 3388 | E8: 45641 | F8: 45683 | G8: 233205 | H8: Cash
A9: 100018 | B9: 41 | C9: 906 | D9: 3220 | E9: 45713 | F9: 45722 | G9: 77474 | H9: Insurance
A10: 100019 | B10: 496 | C10: 619 | D10: 3310 | E10: 45700 | F10: 45709 | G10: 41555 | H10: Cash
A11: 100020 | B11: 377 | C11: 426 | D11: 3307 | E11: 45714 | F11: 45735 | G11: 73657 | H11: Cash
A12: 100021 | B12: 153 | C12: 1249 | D12: 3440 | E12: 45605 | F12: 45614 | G12: 35786 | H12: Insurance
A13: 100022 | B13: 160 | C13: 351 | D13: 3278 | E13: 45649 | F13: 45667 | G13: 79817 | H13: Card
... A1001: 101010 | B1001: 278 | C1001: 1360 | D1001: 3373 | E1001: 45776 | F1001: 45797 | G1001: 60570 | H1001: Cash

Sheet Room
A1: room_No | B1: dept_Id | C1: room_Type
A2: 1 | B2: 101 | C2: Consultation Room
A3: 2 | B3: 101 | C3: Consultation Room
A4: 3 | B4: 101 | C4: Consultation Room
A5: 11 | B5: 101 | C5: Super Deluxe Room
A6: 12 | B6: 101 | C6: Deluxe Room
A7: 13 | B7: 101 | C7: Standard Room
A8: 14 | B8: 101 | C8: Super Deluxe Room
A9: 15 | B9: 101 | C9: Deluxe Room
A10: 16 | B10: 101 | C10: Standard Room
A11: 17 | B11: 101 | C11: Super Deluxe Room
A12: 18 | B12: 101 | C12: Deluxe Room
A13: 19 | B13: 101 | C13: Standard Room
... A392: 530 | B392: 131 | C392: Standard Room

Sheet Ward
A1: ward_No | B1: ward_Name | C1: dept_Id
A2: 501 | B2: ICU | C2: 101
A3: 502 | B3: Cardiology Ward | C3: 101
A4: 503 | B4: Cardiology Ward | C4: 101
A5: 504 | B5: ICU | C5: 101
A6: 505 | B6: Cardiology Ward | C6: 101
A7: 506 | B7: Neurology Ward | C7: 102
A8: 507 | B8: Neurology Ward | C8: 102
A9: 508 | B9: ICU | C9: 102
A10: 509 | B10: Neurology Ward | C10: 102
A11: 510 | B11: General Medicine Ward | C11: 103
A12: 511 | B12: General Medicine Ward | C12: 104
A13: 512 | B13: General Medicine Ward | C13: 104
... A64: 563 | B64: Geriatrics Ward | C64: 131

Sheet RoomRecords
A1: admisson_ID | B1: room_no | C1: patient_Id | D1: Staff_Id | E1: admission_Date | F1: discharge_Date | G1: amount | H1: mode_of_payment
A2: 500001 | B2: 34 | C2: 1170 | D2: 3418 | E2: 45643 | F2: 45650 | G2: 91007 | H2: Insurance
A3: 500002 | B3: 312 | C3: 223 | D3: 3236 | E3: 45708 | F3: 45712 | G3: 58029 | H3: Insurance
A4: 500003 | B4: 185 | C4: 463 | D4: 3221 | E4: 45657 | F4: 45660 | G4: 65889 | H4: Insurance
A5: 500004 | B5: 368 | C5: 873 | D5: 3268 | E5: 45753 | F5: 45755 | G5: 30495 | H5: Card
A6: 500005 | B6: 202 | C6: 515 | D6: 3200 | E6: 45743 | F6: 45748 | G6: 73313 | H6: Cash
A7: 500006 | B7: 264 | C7: 831 | D7: 3198 | E7: 45799 | F7: 45802 | G7: 42932 | H7: Insurance
A8: 500007 | B8: 445 | C8: 1123 | D8: 3281 | E8: 45698 | F8: 45699 | G8: 25093 | H8: Card
A9: 500008 | B9: 48 | C9: 1320 | D9: 3472 | E9: 45801 | F9: 45808 | G9: 70923 | H9: Card
A10: 500009 | B10: 470 | C10: 1587 | D10: 3207 | E10: 45788 | F10: 45794 | G10: 89296 | H10: Insurance
A11: 500010 | B11: 199 | C11: 1575 | D11: 3175 | E11: 45736 | F11: 45738 | G11: 39742 | H11: Cash
A12: 500011 | B12: 218 | C12: 256 | D12: 3386 | E12: 45690 | F12: 45692 | G12: 70917 | H12: Cash
A13: 500012 | B13: 138 | C13: 1318 | D13: 3425 | E13: 45627 | F13: 45635 | G13: 112998 | H13: Insurance
... A1001: 501000 | B1001: 483 | C1001: 923 | D1001: 3115 | E1001: 45621 | F1001: 45624 | G1001: 40606 | H1001: Card

Sheet InternalRecord
A1: Month | B1: Doctor_Salary (₹) | C1: Staff_Salary(₹) | D1: Electricity_Bill(₹) | E1: Maintenance_Cost(₹) | F1: Medicine_Purchase_Cost(₹) | G1: Total_Income(₹) | H1: Total_Expenses(₹) | I1: Profit_Loss(₹)
A2: January | B2: 519289 | C2: 148222 | D2: 59613 | E2: 35796 | F2: 299244 | G2: 1173120 | H2: =SUM(B2,C2,D2,E2,F2) -> 1062164 | I2: =G2-H2 -> 110956
A3: February | B3: 589773 | C3: 92666 | D3: 83076 | E3: 69131 | F3: 325788 | G3: 999122 | H3: =SUM(B3,C3,D3,E3,F3) -> 1160434 | I3: =G3-H3 -> -161312
A4: March | B4: 477567 | C4: 142119 | D4: 89544 | E4: 38123 | F4: 295251 | G4: 1232548 | H4: =SUM(B4,C4,D4,E4,F4) -> 1042604 | I4: =G4-H4 -> 189944
A5: April | B5: 480664 | C5: 115321 | D5: 57492 | E5: 38222 | F5: 223806 | G5: 1244076 | H5: =SUM(B5,C5,D5,E5,F5) -> 915505 | I5: =G5-H5 -> 328571
A6: May | B6: 481199 | C6: 81779 | D6: 60746 | E6: 54074 | F6: 330364 | G6: 1239851 | H6: =SUM(B6,C6,D6,E6,F6) -> 1008162 | I6: =G6-H6 -> 231689
A7: June | B7: 499764 | C7: 93186 | D7: 45188 | E7: 59825 | F7: 236901 | G7: 1382863 | H7: =SUM(B7,C7,D7,E7,F7) -> 934864 | I7: =G7-H7 -> 447999
A8: July | B8: 522357 | C8: 96459 | D8: 81570 | E8: 66839 | F8: 348115 | G8: 1117912 | H8: =SUM(B8,C8,D8,E8,F8) -> 1115340 | I8: =G8-H8 -> 2572
A9: August | B9: 480729 | C9: 85057 | D9: 69680 | E9: 32786 | F9: 340824 | G9: 1135851 | H9: =SUM(B9,C9,D9,E9,F9) -> 1009076 | I9: =G9-H9 -> 126775
A10: September | B10: 559633 | C10: 140663 | D10: 77825 | E10: 63638 | F10: 373688 | G10: 1255933 | H10: =SUM(B10,C10,D10,E10,F10) -> 1215447 | I10: =G10-H10 -> 40486
A11: October | B11: 450568 | C11: 98733 | D11: 76766 | E11: 66964 | F11: 252127 | G11: 1432245 | H11: =SUM(B11,C11,D11,E11,F11) -> 945158 | I11: =G11-H11 -> 487087
A12: November | B12: 509349 | C12: 99157 | D12: 48864 | E12: 55988 | F12: 200453 | G12: 1407750 | H12: =SUM(B12,C12,D12,E12,F12) -> 913811 | I12: =G12-H12 -> 493939
A13: December | B13: 473302 | C13: 115030 | D13: 76445 | E13: 65507 | F13: 275432 | G13: 1007724 | H13: =SUM(B13,C13,D13,E13,F13) -> 1005716 | I13: =G13-H13 -> 2008

Sheet Sheet1
